{
    "Reynolds Leywin": "https://tbate.fandom.com/wiki/Reynolds_Leywin",
    "Alice Leywin": "https://tbate.fandom.com/wiki/Alice_Leywin",
    "Arthur Leywin": "https://tbate.fandom.com/wiki/Arthur_Leywin",
    "Eleanor Leywin": "https://tbate.fandom.com/wiki/Eleanor_Leywin",
    "Helen Shard": "https://tbate.fandom.com/wiki/Helen_Shard",
    "Angela Rose": "https://tbate.fandom.com/wiki/Angela_Rose",
    "Durden Walker": "https://tbate.fandom.com/wiki/Durden_Walker",
    "Jasmine Flamesworth": "https://tbate.fandom.com/wiki/Jasmine_Flamesworth",
    "Adam Krensh": "https://tbate.fandom.com/wiki/Adam_Krensh",
    "Lensa": "https://tbate.fandom.com/wiki/Lensa",
    "Vincent Helstea": "https://tbate.fandom.com/wiki/Vincent_Helstea",
    "Tabitha Helstea": "https://tbate.fandom.com/wiki/Tabitha_Helstea",
    "Lilia Helstea": "https://tbate.fandom.com/wiki/Lilia_Helstea",
    "Virion Eralith": "https://tbate.fandom.com/wiki/Virion_Eralith",
    "Alduin Eralith": "https://tbate.fandom.com/wiki/Alduin_Eralith",
    "Merial Eralith": "https://tbate.fandom.com/wiki/Merial_Eralith",
    "Tessia Eralith": "https://tbate.fandom.com/wiki/Tessia_Eralith",
    "Blaine Glayder": "https://tbate.fandom.com/wiki/Blaine_Glayder",
    "Priscilla Glayder": "https://tbate.fandom.com/wiki/Priscilla_Glayder",
    "Curtis Glayder": "https://tbate.fandom.com/wiki/Curtis_Glayder",
    "Kathyln Glayder": "https://tbate.fandom.com/wiki/Kathyln_Glayder",
    "Dawsid Greysunders": "https://tbate.fandom.com/wiki/Dawsid_Greysunders",
    "Glaudera Greysunders": "https://tbate.fandom.com/wiki/Glaudera_Greysunders",
    "Kaspian Bladeheart": "https://tbate.fandom.com/wiki/Kaspian_Bladeheart",
    "George": "https://tbate.fandom.com/wiki/George",
    "Emily": "https://tbate.fandom.com/wiki/Emily",
    "Mary": "https://tbate.fandom.com/wiki/Mary",
    "Elijah Knight": "https://tbate.fandom.com/wiki/Elijah_Knight",
    "Lucas Wykes": "https://tbate.fandom.com/wiki/Lucas_Wykes",
    "Diane Whitehall": "https://tbate.fandom.com/wiki/Diane_Whitehall",
    "Brald Landon": "https://tbate.fandom.com/wiki/Brald_Landon",
    "Reginald Bastion": "https://tbate.fandom.com/wiki/Reginald_Bastion",
    "Kriol Masser": "https://tbate.fandom.com/wiki/Kriol_Masser",
    "Samantha Tempest": "https://tbate.fandom.com/wiki/Samantha_Tempest",
    "Oliver Hemmbet": "https://tbate.fandom.com/wiki/Oliver_Hemmbet",
    "Turman": "https://tbate.fandom.com/wiki/Turman",
    "Kagul": "https://tbate.fandom.com/wiki/Kagul",
    "Cynthia Goodsky": "https://tbate.fandom.com/wiki/Cynthia_Goodsky",
    "Professor Glory": "https://tbate.fandom.com/wiki/Professor_Glory",
    "Professor Avius": "https://tbate.fandom.com/wiki/Professor_Avius",
    "Professor Geist": "https://tbate.fandom.com/wiki/Professor_Geist",
    "Professor Gideon": "https://tbate.fandom.com/wiki/Professor_Gideon",
    "Malkinheim": "https://tbate.fandom.com/wiki/Malkinheim",
    "Professor Mayner": "https://tbate.fandom.com/wiki/Professor_Mayner",
    "Professor Drywell": "https://tbate.fandom.com/wiki/Professor_Drywell",
    "Grenir": "https://tbate.fandom.com/wiki/Grenir",
    "Claire Bladeheart": "https://tbate.fandom.com/wiki/Claire_Bladeheart",
    "Feyrith Ivsaar III": "https://tbate.fandom.com/wiki/Feyrith_Ivsaar_III",
    "Theodore Maxwell": "https://tbate.fandom.com/wiki/Theodore_Maxwell",
    "Doradrea Oreguard": "https://tbate.fandom.com/wiki/Doradrea_Oreguard",
    "Kai Crestless": "https://tbate.fandom.com/wiki/Kai_Crestless",
    "Clive Graves": "https://tbate.fandom.com/wiki/Clive_Graves",
    "Fable Kristwood": "https://tbate.fandom.com/wiki/Fable_Kristwood",
    "Emily Watsken": "https://tbate.fandom.com/wiki/Emily_Watsken",
    "Jarrod Redner": "https://tbate.fandom.com/wiki/Jarrod_Redner",
    "Broznean Boor": "https://tbate.fandom.com/wiki/Broznean_Boor",
    "Nicolas Dreyl": "https://tbate.fandom.com/wiki/Nicolas_Dreyl",
    "Roland Alderman": "https://tbate.fandom.com/wiki/Roland_Alderman",
    "Charles Ravenpor II": "https://tbate.fandom.com/wiki/Charles_Ravenpor_II",
    "Charlotte": "https://tbate.fandom.com/wiki/Charlotte",
    "Trodius Flamesworth": "https://tbate.fandom.com/wiki/Trodius_Flamesworth",
    "Lady Flamesworth": "https://tbate.fandom.com/wiki/Lady_Flamesworth",
    "Hester Flamesworth": "https://tbate.fandom.com/wiki/Hester_Flamesworth",
    "Senyir Flamesworth": "https://tbate.fandom.com/wiki/Senyir_Flamesworth",
    "Tristan Flamesworth": "https://tbate.fandom.com/wiki/Tristan_Flamesworth",
    "Rowan Flamesworth": "https://tbate.fandom.com/wiki/Rowan_Flamesworth",
    "Cassian Flamesworth": "https://tbate.fandom.com/wiki/Cassian_Flamesworth",
    "Laurel Flamesworth": "https://tbate.fandom.com/wiki/Laurel_Flamesworth",
    "Azulia Flamesworth": "https://tbate.fandom.com/wiki/Azulia_Flamesworth",
    "Bairon Wykes": "https://tbate.fandom.com/wiki/Bairon_Wykes",
    "Varay Aurae": "https://tbate.fandom.com/wiki/Varay_Aurae",
    "Aya Grephin": "https://tbate.fandom.com/wiki/Aya_Grephin",
    "Alea Triscan": "https://tbate.fandom.com/wiki/Alea_Triscan",
    "Olfred Warend": "https://tbate.fandom.com/wiki/Olfred_Warend",
    "Mica Earthborn": "https://tbate.fandom.com/wiki/Mica_Earthborn",
    "Carnelian Earthborn": "https://tbate.fandom.com/wiki/Carnelian_Earthborn",
    "Skarn Earthborn": "https://tbate.fandom.com/wiki/Skarn_Earthborn",
    "Hornfels Earthborn": "https://tbate.fandom.com/wiki/Hornfels_Earthborn",
    "Rinia Darcassan": "https://tbate.fandom.com/wiki/Rinia_Darcassan",
    "Lania Darcassan": "https://tbate.fandom.com/wiki/Lania_Darcassan",
    "Alanis Emeria": "https://tbate.fandom.com/wiki/Alanis_Emeria",
    "Camus Selaridon": "https://tbate.fandom.com/wiki/Camus_Selaridon",
    "Jarnas Auddyr": "https://tbate.fandom.com/wiki/Jarnas_Auddyr",
    "Albold Chaffer": "https://tbate.fandom.com/wiki/Albold_Chaffer",
    "Lenna Aemaris": "https://tbate.fandom.com/wiki/Lenna_Aemaris",
    "Camellia Lehtinen": "https://tbate.fandom.com/wiki/Camellia_Lehtinen",
    "Rahdeas": "https://tbate.fandom.com/wiki/Rahdeas",
    "Buhndemog Lonuid": "https://tbate.fandom.com/wiki/Buhndemog_Lonuid",
    "Stannard Berwick": "https://tbate.fandom.com/wiki/Stannard_Berwick",
    "Darvus Clarell": "https://tbate.fandom.com/wiki/Darvus_Clarell",
    "Caria Rede": "https://tbate.fandom.com/wiki/Caria_Rede",
    "Drogo Lambert": "https://tbate.fandom.com/wiki/Drogo_Lambert",
    "Madam Astera": "https://tbate.fandom.com/wiki/Madam_Astera",
    "Cedry": "https://tbate.fandom.com/wiki/Cedry",
    "Jona": "https://tbate.fandom.com/wiki/Jona",
    "Nyphia": "https://tbate.fandom.com/wiki/Nyphia",
    "Herrick": "https://tbate.fandom.com/wiki/Herrick",
    "Albreda": "https://tbate.fandom.com/wiki/Albreda",
    "Jesmiya Cruwer": "https://tbate.fandom.com/wiki/Jesmiya_Cruwer",
    "Hachi": "https://tbate.fandom.com/wiki/Hachi",
    "Seris": "https://tbate.fandom.com/wiki/Seris",
    "Cadell": "https://tbate.fandom.com/wiki/Cadell",
    "Melzri": "https://tbate.fandom.com/wiki/Melzri",
    "Nico Sever": "https://tbate.fandom.com/wiki/Nico_Sever",
    "Viessa": "https://tbate.fandom.com/wiki/Viessa",
    "Dragoth": "https://tbate.fandom.com/wiki/Dragoth",
    "Uto": "https://tbate.fandom.com/wiki/Uto",
    "Cylrit": "https://tbate.fandom.com/wiki/Cylrit",
    "Jagrette": "https://tbate.fandom.com/wiki/Jagrette",
    "Lyra Dreide": "https://tbate.fandom.com/wiki/Lyra_Dreide",
    "Bilal": "https://tbate.fandom.com/wiki/Bilal",
    "Mawar": "https://tbate.fandom.com/wiki/Mawar",
    "Echeron": "https://tbate.fandom.com/wiki/Echeron",
    "Bivrae": "https://tbate.fandom.com/wiki/Bivrae",
    "Wolfrum Redwater": "https://tbate.fandom.com/wiki/Wolfrum_Redwater",
    "Grey": "https://tbate.fandom.com/wiki/Grey",
    "Cecilia": "https://tbate.fandom.com/wiki/Cecilia",
    "Olivia Wilbeck": "https://tbate.fandom.com/wiki/Olivia_Wilbeck",
    "Lady Vera": "https://tbate.fandom.com/wiki/Lady_Vera",
    "Drem": "https://tbate.fandom.com/wiki/Drem",
    "Instructor Gredge": "https://tbate.fandom.com/wiki/Instructor_Gredge",
    "Corbett Denoir": "https://tbate.fandom.com/wiki/Corbett_Denoir",
    "Lenora Denoir": "https://tbate.fandom.com/wiki/Lenora_Denoir",
    "Caera Denoir": "https://tbate.fandom.com/wiki/Caera_Denoir",
    "Sevren Denoir": "https://tbate.fandom.com/wiki/Sevren_Denoir",
    "Lauden Denoir": "https://tbate.fandom.com/wiki/Lauden_Denoir",
    "Justus Denoir": "https://tbate.fandom.com/wiki/Justus_Denoir",
    "Arden Denoir": "https://tbate.fandom.com/wiki/Arden_Denoir",
    "Melitta Denoir": "https://tbate.fandom.com/wiki/Melitta_Denoir",
    "Colm Denoir": "https://tbate.fandom.com/wiki/Colm_Denoir",
    "Arno Denoir": "https://tbate.fandom.com/wiki/Arno_Denoir",
    "Gemma Denoir": "https://tbate.fandom.com/wiki/Gemma_Denoir",
    "Titus Granbehl": "https://tbate.fandom.com/wiki/Titus_Granbehl",
    "Karin Granbehl": "https://tbate.fandom.com/wiki/Karin_Granbehl",
    "Kalon Granbehl": "https://tbate.fandom.com/wiki/Kalon_Granbehl",
    "Ezra Granbehl": "https://tbate.fandom.com/wiki/Ezra_Granbehl",
    "Ada Granbehl": "https://tbate.fandom.com/wiki/Ada_Granbehl",
    "Darrin Ordin": "https://tbate.fandom.com/wiki/Darrin_Ordin",
    "Sorrel": "https://tbate.fandom.com/wiki/Sorrel",
    "Briar Nadir": "https://tbate.fandom.com/wiki/Briar_Nadir",
    "Pen": "https://tbate.fandom.com/wiki/Pen",
    "Adem": "https://tbate.fandom.com/wiki/Adem",
    "Katla": "https://tbate.fandom.com/wiki/Katla",
    "Ketil": "https://tbate.fandom.com/wiki/Ketil",
    "Director Ramseyer": "https://tbate.fandom.com/wiki/Director_Ramseyer",
    "Janusz Graeme": "https://tbate.fandom.com/wiki/Janusz_Graeme",
    "Abby Redcliff": "https://tbate.fandom.com/wiki/Abby_Redcliff",
    "Rafferty Irongrove": "https://tbate.fandom.com/wiki/Rafferty_Irongrove",
    "Kayden Aphelion": "https://tbate.fandom.com/wiki/Kayden_Aphelion",
    "Tristan Severin": "https://tbate.fandom.com/wiki/Tristan_Severin",
    "Edmon Scriven": "https://tbate.fandom.com/wiki/Edmon_Scriven",
    "Dhelia": "https://tbate.fandom.com/wiki/Dhelia",
    "Valen Ramseyer": "https://tbate.fandom.com/wiki/Valen_Ramseyer",
    "Seth Milview": "https://tbate.fandom.com/wiki/Seth_Milview",
    "Enola Frost": "https://tbate.fandom.com/wiki/Enola_Frost",
    "Mayla Fairweather": "https://tbate.fandom.com/wiki/Mayla_Fairweather",
    "Pascal Bancroft": "https://tbate.fandom.com/wiki/Pascal_Bancroft",
    "Yanick Farshore": "https://tbate.fandom.com/wiki/Yanick_Farshore",
    "Linden": "https://tbate.fandom.com/wiki/Linden",
    "Brion Bloodworth": "https://tbate.fandom.com/wiki/Brion_Bloodworth",
    "Sloane Lowe": "https://tbate.fandom.com/wiki/Sloane_Lowe",
    "Marcus Arkwright": "https://tbate.fandom.com/wiki/Marcus_Arkwright",
    "Laurel Redcliff": "https://tbate.fandom.com/wiki/Laurel_Redcliff",
    "Deacon Favager": "https://tbate.fandom.com/wiki/Deacon_Favager",
    "Portrel Gladwyn": "https://tbate.fandom.com/wiki/Portrel_Gladwyn",
    "Remy Seabrook": "https://tbate.fandom.com/wiki/Remy_Seabrook",
    "Cromely Mandrick": "https://tbate.fandom.com/wiki/Cromely_Mandrick",
    "Aphene Mandrick": "https://tbate.fandom.com/wiki/Aphene_Mandrick",
    "Pallisun": "https://tbate.fandom.com/wiki/Pallisun",
    "Belmun": "https://tbate.fandom.com/wiki/Belmun",
    "Braxton": "https://tbate.fandom.com/wiki/Braxton",
    "Djimon Gwede": "https://tbate.fandom.com/wiki/Djimon_Gwede",
    "Anvald Torpor": "https://tbate.fandom.com/wiki/Anvald_Torpor",
    "Sulla Drusus": "https://tbate.fandom.com/wiki/Sulla_Drusus",
    "Harlow Edevane": "https://tbate.fandom.com/wiki/Harlow_Edevane",
    "Draneeve": "https://tbate.fandom.com/wiki/Draneeve",
    "Taegen": "https://tbate.fandom.com/wiki/Taegen",
    "Arian": "https://tbate.fandom.com/wiki/Arian",
    "Mayla": "https://tbate.fandom.com/wiki/Mayla",
    "Alaric": "https://tbate.fandom.com/wiki/Alaric",
    "Trider": "https://tbate.fandom.com/wiki/Trider",
    "Daria": "https://tbate.fandom.com/wiki/Daria",
    "Karnal Vale": "https://tbate.fandom.com/wiki/Karnal_Vale",
    "Steffan Vale": "https://tbate.fandom.com/wiki/Steffan_Vale",
    "Riah Faline": "https://tbate.fandom.com/wiki/Riah_Faline",
    "Mythelias": "https://tbate.fandom.com/wiki/Mythelias",
    "Quinten": "https://tbate.fandom.com/wiki/Quinten",
    "Haleigh Leech": "https://tbate.fandom.com/wiki/Haleigh_Leech",
    "Kagiso": "https://tbate.fandom.com/wiki/Kagiso",
    "Aadaan": "https://tbate.fandom.com/wiki/Aadaan",
    "Drekker Vassare": "https://tbate.fandom.com/wiki/Drekker_Vassare",
    "Balder Vassare": "https://tbate.fandom.com/wiki/Balder_Vassare",
    "Chief Mason": "https://tbate.fandom.com/wiki/Chief_Mason",
    "Tovorin Karsten": "https://tbate.fandom.com/wiki/Tovorin_Karsten",
    "Three Steps": "https://tbate.fandom.com/wiki/Three_Steps",
    "Amand": "https://tbate.fandom.com/wiki/Amand",
    "Kage": "https://tbate.fandom.com/wiki/Kage",
    "T\u2019laya": "https://tbate.fandom.com/wiki/T%E2%80%99laya",
    "Lady Sae-Areum": "https://tbate.fandom.com/wiki/Lady_Sae-Areum",
    "Ji-ae": "https://tbate.fandom.com/wiki/Ji-ae",
    "Haneul": "https://tbate.fandom.com/wiki/Haneul",
    "First Djinn Remnant": "https://tbate.fandom.com/wiki/First_Djinn_Remnant",
    "Second Djinn Remnant": "https://tbate.fandom.com/wiki/Second_Djinn_Remnant",
    "Kezess the First": "https://tbate.fandom.com/wiki/Kezess_the_First",
    "Arkanus Indrath": "https://tbate.fandom.com/wiki/Arkanus_Indrath",
    "Kezess Indrath": "https://tbate.fandom.com/wiki/Kezess_Indrath",
    "Myre": "https://tbate.fandom.com/wiki/Myre",
    "Sylvia": "https://tbate.fandom.com/wiki/Sylvia",
    "Sylvie": "https://tbate.fandom.com/wiki/Sylvie",
    "Windsom": "https://tbate.fandom.com/wiki/Windsom",
    "Wren Kain IV": "https://tbate.fandom.com/wiki/Wren_Kain_IV",
    "Vajrakor": "https://tbate.fandom.com/wiki/Vajrakor",
    "Tassos": "https://tbate.fandom.com/wiki/Tassos",
    "Irini": "https://tbate.fandom.com/wiki/Irini",
    "Alkis": "https://tbate.fandom.com/wiki/Alkis",
    "Kastor": "https://tbate.fandom.com/wiki/Kastor",
    "Spiros": "https://tbate.fandom.com/wiki/Spiros",
    "Orrin": "https://tbate.fandom.com/wiki/Orrin",
    "Signiz": "https://tbate.fandom.com/wiki/Signiz",
    "Edirith": "https://tbate.fandom.com/wiki/Edirith",
    "Charon": "https://tbate.fandom.com/wiki/Charon",
    "Agrona Vritra": "https://tbate.fandom.com/wiki/Agrona_Vritra",
    "Kiros": "https://tbate.fandom.com/wiki/Kiros",
    "Orlaeth": "https://tbate.fandom.com/wiki/Orlaeth",
    "Exeges": "https://tbate.fandom.com/wiki/Exeges",
    "Oludari": "https://tbate.fandom.com/wiki/Oludari",
    "Khaernos": "https://tbate.fandom.com/wiki/Khaernos",
    "Ademir": "https://tbate.fandom.com/wiki/Ademir",
    "Kordri": "https://tbate.fandom.com/wiki/Kordri",
    "Taci": "https://tbate.fandom.com/wiki/Taci",
    "Aldir": "https://tbate.fandom.com/wiki/Aldir",
    "Mordain Asclepius": "https://tbate.fandom.com/wiki/Mordain_Asclepius",
    "Dawn": "https://tbate.fandom.com/wiki/Dawn",
    "Soleil": "https://tbate.fandom.com/wiki/Soleil",
    "Aurora": "https://tbate.fandom.com/wiki/Aurora",
    "Chul": "https://tbate.fandom.com/wiki/Chul",
    "Radix Grandus": "https://tbate.fandom.com/wiki/Radix_Grandus",
    "Morwenna Mapellia": "https://tbate.fandom.com/wiki/Morwenna_Mapellia",
    "Nephele Aerind": "https://tbate.fandom.com/wiki/Nephele_Aerind",
    "Verhun": "https://tbate.fandom.com/wiki/Verhun",
    "Zelyna": "https://tbate.fandom.com/wiki/Zelyna",
    "Rai Kothan": "https://tbate.fandom.com/wiki/Rai_Kothan",
    "Riven": "https://tbate.fandom.com/wiki/Riven",
    "Romii": "https://tbate.fandom.com/wiki/Romii",
    "Novis Avignis": "https://tbate.fandom.com/wiki/Novis_Avignis",
    "Naesia": "https://tbate.fandom.com/wiki/Naesia",
    "Regis": "https://tbate.fandom.com/wiki/Regis"
}